jsonclasses_orm/__init__.py
jsonclasses_orm/orm_object.py
jsonclasses_orm/orm_query.py
jsonclasses_orm/py.typed
jsonclasses_orm-2.8.1.dist-info/LICENSE
jsonclasses_orm-2.8.1.dist-info/METADATA
jsonclasses_orm-2.8.1.dist-info/WHEEL
jsonclasses_orm-2.8.1.dist-info/top_level.txt
jsonclasses_orm-2.8.1.dist-info/RECORD
